uenv.py
uenv-0.0.1.dist-info/LICENSE
uenv-0.0.1.dist-info/METADATA
uenv-0.0.1.dist-info/WHEEL
uenv-0.0.1.dist-info/top_level.txt
uenv-0.0.1.dist-info/RECORD
