Metadata-Version: 2.1
Name: uenv
Version: 0.0.1
Summary: A simple .env reader
Author-email: Viet Hung Nguyen <hvn@familug.org>
Project-URL: Homepage, https://github.com/hvnsweeting/uenv
Project-URL: Bug Tracker, https://github.com/hvnsweeting/uenv/issues
Classifier: Programming Language :: Python :: 3
Classifier: License :: OSI Approved :: MIT License
Classifier: Operating System :: OS Independent
Requires-Python: >=2.7
License-File: LICENSE
